{
  "objectInfo" : {
    "id" : "iagaZa1ksS1eu73dlG8YsJ",
    "name" : "VCSBranchTests",
    "type" : "Project",
    "metadata" : {
      "modelVersion" : {
        "major" : 0,
        "minor" : 0
      },
      "repoInfo" : null,
      "contextAttributes" : [ ],
      "additionalInfo" : {
        "description" : "",
        "contentType" : "Binary",
        "documentState" : "COMPLETE"
      }
    }
  },
  "dataFileExtension" : "json",
  "updateTime" : "2025-11-04T23:16:14.647Z",
  "objectRefs" : [ ],
  "readableFileExtension" : null,
  "readableFilePresent" : false
}